{
    "videos": [
        {
            "id": 0,
            "vname": "NIIT R&D Conference",
            "vduration": "2hrs 30mins",
            "vheldOn": "21 Feb 2020",
            "vhubs": [],
            "data": [
                {
                    "pid": "1",
                    "pname": "Speaker_1",
                    "ptype": "hub",
                    "dio": "8",
                    "ci_graph": "1",
                    "vs": 0,
                    "id": 1,
                    "cdoi": 8,
                    "ia": null
                },
                {
                    "pid": "8",
                    "pname": "Speaker_8",
                    "ptype": "spoke",
                    "dio": "11",
                    "ci_graph": "1",
                    "vs": 0,
                    "id": 2,
                    "cdoi": 11,
                    "ia": "1"
                },
                {
                    "pid": "9",
                    "pname": "Speaker_9",
                    "ptype": "spoke",
                    "dio": "1",
                    "ci_graph": "1",
                    "vs": 1,
                    "id": 3,
                    "cdoi": 1,
                    "ia": "8"
                },
                {
                    "pid": "4",
                    "pname": "Speaker_4",
                    "ptype": "spoke",
                    "dio": "11",
                    "ci_graph": "1",
                    "vs": 1,
                    "id": 4,
                    "cdoi": 11,
                    "ia": "9"
                },
                {
                    "pid": "1",
                    "pname": "Speaker_1",
                    "ptype": "hub",
                    "dio": "3",
                    "ci_graph": "1",
                    "vs": 0,
                    "id": 5,
                    "cdoi": 11,
                    "ia": "4"
                },
                {
                    "pid": "6",
                    "pname": "Speaker_6",
                    "ptype": "spoke",
                    "dio": "4",
                    "ci_graph": "1",
                    "vs": 1,
                    "id": 6,
                    "cdoi": 4,
                    "ia": "1"
                },
                {
                    "pid": "1",
                    "pname": "Speaker_1",
                    "ptype": "hub",
                    "dio": "8",
                    "ci_graph": "1",
                    "vs": 0,
                    "id": 7,
                    "cdoi": 19,
                    "ia": "6"
                },
                {
                    "pid": "10",
                    "pname": "Speaker_10",
                    "ptype": "spoke",
                    "dio": "2",
                    "ci_graph": "1",
                    "vs": 1,
                    "id": 8,
                    "cdoi": 2,
                    "ia": "1"
                },
                {
                    "pid": "1",
                    "pname": "Speaker_1",
                    "ptype": "hub",
                    "dio": "13",
                    "ci_graph": "1",
                    "vs": 0,
                    "id": 9,
                    "cdoi": 32,
                    "ia": "10"
                },
                {
                    "pid": "8",
                    "pname": "Speaker_8",
                    "ptype": "spoke",
                    "dio": "6",
                    "ci_graph": "1",
                    "vs": 1,
                    "id": 10,
                    "cdoi": 17,
                    "ia": "1"
                },
                {
                    "pid": "6",
                    "pname": "Speaker_6",
                    "ptype": "spoke",
                    "dio": "10",
                    "ci_graph": "1",
                    "vs": 0,
                    "id": 11,
                    "cdoi": 14,
                    "ia": "8"
                },
                {
                    "pid": "5",
                    "pname": "Speaker_5",
                    "ptype": "spoke",
                    "dio": "14",
                    "ci_graph": "1",
                    "vs": 1,
                    "id": 12,
                    "cdoi": 14,
                    "ia": "6"
                },
                {
                    "pid": "2",
                    "pname": "Speaker_2",
                    "ptype": "spoke",
                    "dio": "10",
                    "ci_graph": "1",
                    "vs": 0,
                    "id": 13,
                    "cdoi": 10,
                    "ia": "5"
                },
                {
                    "pid": "5",
                    "pname": "Speaker_5",
                    "ptype": "spoke",
                    "dio": "10",
                    "ci_graph": "1",
                    "vs": 1,
                    "id": 14,
                    "cdoi": 24,
                    "ia": "2"
                },
                {
                    "pid": "6",
                    "pname": "Speaker_6",
                    "ptype": "spoke",
                    "dio": "7",
                    "ci_graph": "1",
                    "vs": 1,
                    "id": 15,
                    "cdoi": 21,
                    "ia": "5"
                },
                {
                    "pid": "8",
                    "pname": "Speaker_8",
                    "ptype": "spoke",
                    "dio": "23",
                    "ci_graph": "1",
                    "vs": 0,
                    "id": 16,
                    "cdoi": 40,
                    "ia": "6"
                },
                {
                    "pid": "4",
                    "pname": "Speaker_4",
                    "ptype": "spoke",
                    "dio": "16",
                    "ci_graph": "1",
                    "vs": 1,
                    "id": 17,
                    "cdoi": 27,
                    "ia": "8"
                },
                {
                    "pid": "1",
                    "pname": "Speaker_1",
                    "ptype": "hub",
                    "dio": "19",
                    "ci_graph": "1",
                    "vs": 1,
                    "id": 18,
                    "cdoi": 51,
                    "ia": "4"
                },
                {
                    "pid": "6",
                    "pname": "Speaker_6",
                    "ptype": "spoke",
                    "dio": "6",
                    "ci_graph": "1",
                    "vs": 1,
                    "id": 19,
                    "cdoi": 27,
                    "ia": "1"
                },
                {
                    "pid": "7",
                    "pname": "Speaker_7",
                    "ptype": "spoke",
                    "dio": "3",
                    "ci_graph": "1",
                    "vs": 1,
                    "id": 20,
                    "cdoi": 3,
                    "ia": "6"
                },
                {
                    "pid": "1",
                    "pname": "Speaker_1",
                    "ptype": "hub",
                    "dio": "5",
                    "ci_graph": "1",
                    "vs": 0,
                    "id": 21,
                    "cdoi": 56,
                    "ia": "7"
                },
                {
                    "pid": "2",
                    "pname": "Speaker_2",
                    "ptype": "spoke",
                    "dio": "17",
                    "ci_graph": "1",
                    "vs": 0,
                    "id": 22,
                    "cdoi": 27,
                    "ia": "1"
                },
                {
                    "pid": "8",
                    "pname": "Speaker_8",
                    "ptype": "spoke",
                    "dio": "8",
                    "ci_graph": "1",
                    "vs": 1,
                    "id": 23,
                    "cdoi": 48,
                    "ia": "2"
                },
                {
                    "pid": "10",
                    "pname": "Speaker_10",
                    "ptype": "spoke",
                    "dio": "20",
                    "ci_graph": "1",
                    "vs": 0,
                    "id": 24,
                    "cdoi": 22,
                    "ia": "8"
                },
                {
                    "pid": "6",
                    "pname": "Speaker_6",
                    "ptype": "spoke",
                    "dio": "6",
                    "ci_graph": "1",
                    "vs": 1,
                    "id": 25,
                    "cdoi": 33,
                    "ia": "10"
                },
                {
                    "pid": "7",
                    "pname": "Speaker_7",
                    "ptype": "spoke",
                    "dio": "8",
                    "ci_graph": "1",
                    "vs": 1,
                    "id": 26,
                    "cdoi": 11,
                    "ia": "6"
                },
                {
                    "pid": "1",
                    "pname": "Speaker_1",
                    "ptype": "hub",
                    "dio": "32",
                    "ci_graph": "1",
                    "vs": 0,
                    "id": 27,
                    "cdoi": 88,
                    "ia": "7"
                },
                {
                    "pid": "5",
                    "pname": "Speaker_5",
                    "ptype": "spoke",
                    "dio": "8",
                    "ci_graph": "1",
                    "vs": 0,
                    "id": 28,
                    "cdoi": 32,
                    "ia": "1"
                },
                {
                    "pid": "1",
                    "pname": "Speaker_1",
                    "ptype": "hub",
                    "dio": "21",
                    "ci_graph": "1",
                    "vs": 0,
                    "id": 29,
                    "cdoi": 109,
                    "ia": "5"
                },
                {
                    "pid": "7",
                    "pname": "Speaker_7",
                    "ptype": "spoke",
                    "dio": "8",
                    "ci_graph": "1",
                    "vs": 1,
                    "id": 30,
                    "cdoi": 19,
                    "ia": "1"
                },
                {
                    "pid": "8",
                    "pname": "Speaker_8",
                    "ptype": "spoke",
                    "dio": "6",
                    "ci_graph": "1",
                    "vs": 0,
                    "id": 31,
                    "cdoi": 54,
                    "ia": "7"
                },
                {
                    "pid": "6",
                    "pname": "Speaker_6",
                    "ptype": "spoke",
                    "dio": "4",
                    "ci_graph": "1",
                    "vs": 1,
                    "id": 32,
                    "cdoi": 37,
                    "ia": "8"
                },
                {
                    "pid": "10",
                    "pname": "Speaker_10",
                    "ptype": "spoke",
                    "dio": "11",
                    "ci_graph": "1",
                    "vs": 1,
                    "id": 33,
                    "cdoi": 33,
                    "ia": "6"
                },
                {
                    "pid": "6",
                    "pname": "Speaker_6",
                    "ptype": "spoke",
                    "dio": "9",
                    "ci_graph": "1",
                    "vs": 0,
                    "id": 34,
                    "cdoi": 46,
                    "ia": "10"
                },
                {
                    "pid": "10",
                    "pname": "Speaker_10",
                    "ptype": "spoke",
                    "dio": "27",
                    "ci_graph": "1",
                    "vs": 0,
                    "id": 35,
                    "cdoi": 60,
                    "ia": "6"
                }
            ]
        }
    ]
}